{
    "categoryName": "Clawless Shade Cloak",
    "splitIds": [
        "VengefulSpirit",
        "EnterGreenpath",
        "MothwingCloak",
        "BlueLake",
        "DreamNail",
        "LumaflyLantern",
        "FragileHeart",
        "NotchShrumalOgres",
        "ElderHuEssence",
        "NoEyesEssence",
        "SpiritGladeOpen",
        "NailUpgrade1",
        "BrokenVessel",
        "LostKinEssence",
        "DreamGate",
        "KingsBrand",
        "ShadeCloak"
    ],
    "ordered": true,
    "endTriggeringAutosplit": true,
    "gameName": "Hollow Knight Category Extensions"
}
