{
    "categoryName": "Spelless True Ending",
    "splitIds": [
        "FuryOfTheFallen",
        "FalseKnight",
        "Longnail",
        "EnterGreenpath",
        "MothwingCloak",
        "MegaMossCharger",
        "MantisClaw",
        "DreamNail",
        "ElderHuEssence",
        "SporeShroom",
        "GalienEssence",
        "XeroEssence",
        "NailUpgrade2",
        "LumaflyLantern",
        "CrystalHeart",
        "TollBenchBasin",
        "BrokenVessel",
        "MonarchWings",
        "GorbEssence",
        "DreamGate",
        "KingsBrand",
        "ShadeCloak",
        "MarkothEssence",
        "BlackKnight",
        "FailedChampionEssence",
        "Uumuu",
        "NoEyesEssence",
        "MarmuEssence",
        "WhiteFragmentLeft",
        "Hegemol",
        "DreamNail2",
        "Kingsoul",
        "VoidHeart",
        "HollowKnightDreamnail"
    ],
    "ordered": true,
    "endTriggeringAutosplit": false,
    "endingSplit": {
        "name": "Hollow Knight",
        "icon": "HollowKnightBoss"
    },
    "gameName": "Hollow Knight Category Extensions"
}
