{
    "categoryName": "100%",
    "splitIds": [
        "StartNewGame",
        "MossMother",
        "SilkSpear",
        "BellBeast",
        "EnterHuntersMarch",
        "-SavedFleaHuntersMarch",
        "-SeenShakraHuntersMarch",
        "SwiftStep",
        "-SavedFleaDeepDocksSprint",
        "-SavedFleaDeepDocksBellway",
        "Lace1",
        "-SavedFleaFarFieldsTrap",
        "FarFieldsStation",
        "-SavedFleaMarrow",
        "GreymoorStation",
        "EnterShellwood",
        "-SavedFleaShellwood",
        "-MaskShard1",
        "-ShellwoodStation",
        "ClingGrip",
        "-SavedFleaBellhart",
        "Widow",
        "NeedleUpgrade1",
        "-SpoolFragment1",
        "-SavedFleaGreymoorLake",
        "ThreadStorm",
        "ReaperCrest",
        "EnterFarFields",
        "DriftersCloak",
        "FourthChorus",
        "ShellwoodBell",
        "-BlastedStepsStation",
        "LastJudge",
        "Act2Started",
        "-SavedFleaChoralChambersCage",
        "-Spool1",
        "SlabStation",
        "-GrandBellwayTube",
        "CollectedWhitewardKey",
        "-SavedFleaUnderworksCauldron",
        "Clawline",
        "-SpoolFragment3",
        "UnderworksTube",
        "-PlayerDeath",
        "FaydownCloak",
        "-SavedFleaMountFay",
        "-MaskShard2",
        "Menu",
        "SongclaveBell",
        "EnterMemorium",
        "-SavedFleaGiantFlea",
        "-Spool2",
        "CogworkDancers",
        "-MaskShard3",
        "-SavedFleaChoralChambersWind",
        "EnterHighHalls",
        "-SpoolFragment5",
        "Menu",
        "-Spool3",
        "ArchitectsMelody",
        "WhisperingVaultsArena",
        "-SavedFleaWhisperingVaults",
        "EnterShellwood",
        "Mask1",
        "NeedleUpgrade2",
        "Menu",
        "GreatConchflies",
        "NeedleStrike",
        "-SeenShakraSandsOfKarak",
        "Menu",
        "-SavedFleaBlastedSteps",
        "-SavedFleaSandsOfKarak",
        "Voltvyrm",
        "EnterWormways",
        "-SavedFleaWormways",
        "Sharpdart",
        "Menu",
        "WandererCrest",
        "-SpoolFragment7",
        "-MaskShard6",
        "-Spool4",
        "Menu",
        "SkullTyrant1",
        "MaskShard7",
        "Trobbio",
        "-Mask2",
        "-SavedFleaSongclave",
        "VaultkeepersMelody",
        "EnterBilewater",
        "-EnterMist",
        "-LeaveMist",
        "Phantom",
        "-SavedFleaBilewaterOrgan",
        "-SeenShakraSinnersRoad",
        "-SavedFleaSinnersRoad",
        "-SavedFleaBilewaterThieves",
        "Menu",
        "-SeenShakraBilewater",
        "Menu",
        "EnterShellwood",
        "EnterGreymoor",
        "-SavedFleaGreymoorRoof",
        "Menu",
        "-SavedFleaKratt",
        "Menu",
        "MaskShard9",
        "Menu",
        "Menu",
        "-EnterHuntersMarch",
        "BeastCrest",
        "-EnterFarFields",
        "EnterShellwood",
        "-SpoolFragment9",
        "-JubilanaRescuedChoralChambers",
        "EnterHighHalls",
        "-EnterHighHallsArena",
        "ConductorsMelody",
        "SavageBeastfly2",
        "-MaskShard10",
        "MaskShard11",
        "-Spool5",
        "-SavedFleaDeepDocksArena",
        "Forebrothers",
        "-SpoolFragment11",
        "Menu",
        "-SavedFleaSlabBellway",
        "-SavedFleaSlabCage",
        "Mask3",
        "-UnlockedMelodyLift",
        "Lace2",
        "Spool6",
        "-SpoolFragment13",
        "Menu",
        "-Spool7",
        "Menu",
        "-EnterMemorium",
        "-JubilanaRescuedMemorium",
        "PutrifiedDuctsStation",
        "-EnterBilewater",
        "-SavedFleaBilewaterTrap",
        "Menu",
        "MaskShard13",
        "SeenFleatopiaEmpty",
        "SavedFleaVog",
        "-MaskShard14",
        "CaravanTroupeFleatopia",
        "Menu",
        "Spool8",
        "Menu",
        "EndingSplit",
        "EnterBellEater",
        "BeastlingCall",
        "ManualSplit",
        "BallowMoved",
        "DivingBellAbyssTrans",
        "SilkSoar",
        "AbyssEscape",
        "-Mask4",
        "SoldRelic",
        "EnterShellwood",
        "NeedleUpgrade4",
        "PaleNails",
        "ArchitectCrest",
        "ElegyOfTheDeep",
        "ShamanCrest",
        "EnterFarFields",
        "-EnterKarmelitaMemory",
        "HeartKarmelita",
        "GurrTheOutcast",
        "MaskShard17",
        "Menu",
        "SpoolFragment17",
        "-EnterKhannMemory",
        "HeartKhann",
        "-EnterSeth",
        "Seth",
        "HeartNyleth",
        "MaskShard18",
        "-EnterFirstSinner",
        "RuneRage",
        "Mask5",
        "EnterRedMemory",
        "RedMemory",
        "LostLaceEncountered",
        "EndingSplit"
    ],
    "names": {
        "Menu": [
            "Memory Crystal SQ",
            "Shortcut SQ",
            "Magnetite Dice SQ",
            "Crustnut SQ",
            "3 Plasmium SQ",
            "Weavelight SQ",
            "Ruined Tool SQ",
            "Huntress SQ",
            "Pimpillo SQ",
            "Sinner's Road SQ",
            "Flea SQ",
            "Vintage Nectar SQ",
            "Forge Daughter SQ",
            "Delver's Drill SQ",
            "Second Sentinel SQ",
            "Trail's End SQ",
            "Farming start",
            "Soul SQ",
            "Fatal Resolve SQ"
        ],
        "MaskShard7": "Pebb buyout",
        "MaskShard11": "Lava Cave Shard",
        "Spool6": "Sherma Spool",
        "Spool8": "Jubilana Buyout",
        "EndingSplit": ["Grand Mother Silk", "Lost Lace"],
        "ManualSplit": "Flea Festival (MANUAL)",
        "MaskShard17": "Sprintmaster Shard",
        "SpoolFragment17": "Grindle Buyout"
    },
    "icons": {
        "EndingSplit": ["EndingSplit", "LostLace"]
    },
    "gameName": "Hollow Knight: Silksong"
}
