{
    "categoryName": "Low%",
    "splitIds": [
        "StartNewGame",
        "MossMotherTrans",
        "EnterMosshome",
        "BoneBottomSimpleKey",
        "EnterUpperWormways",
        "EnterShellwood",
        "ClingGripTrans",
        "Lace1Trans",
        "DriftersCloakTrans",
        "EnterBellhart",
        "Widow",
        "EnterSinnersRoad",
        "EnterExhaustOrgan",
        "Phantom",
        "EnterCogworkDancers",
        "CogworkDancers",
        "WhisperingVaultsArena",
        "TrobbioTrans",
        "Clawline",
        "VaultkeepersMelodyTrans",
        "ArchitectsMelodyTrans",
        "EnterHighHallsArena",
        "ConductorsMelody",
        "Lace2",
        "EndingSplit"
    ],
    "names": {
        "EndingSplit": "Grand Mother Silk"
    },
    "gameName": "Hollow Knight: Silksong",
    "variables": {
        "Low% Subcategory": "No Major Glitches"
    }
}
