{
    "Hollow Knight": [
        {
            "fileName": "112",
            "displayName": "112% APB"
        },
        {
            "fileName": "107",
            "displayName": "107% AB"
        },
        {
            "fileName": "106",
            "displayName": "106% TE"
        },
        {
            "fileName": "all-skills",
            "displayName": "All Skills"
        },
        {
            "fileName": "all-skills-cp",
            "displayName": "All Skills (Current Patch NMG)"
        },
        {
            "fileName": "any",
            "displayName": "Any%"
        },
        {
            "fileName": "any-cp-spore",
            "displayName": "Any% (1.4.3.2) w/ Spore Shroom"
        },
        {
            "fileName": "any-ss",
            "displayName": "Any% Steel Soul"
        },
        {
            "fileName": "low",
            "displayName": "Low%"
        },
        {
            "fileName": "te",
            "displayName": "True Ending"
        },
        {
            "fileName": "te-cp",
            "displayName": "True Ending (1.4+ Shriek)"
        },
        {
            "fileName": "godhome-ending",
            "displayName": "Godhome Ending"
        }
    ],
    "Hollow Knight: Individual Level": [
        {
            "fileName": "p1",
            "displayName": "Pantheon of the Master (P1)"
        },
        {
            "fileName": "p2",
            "displayName": "Pantheon of the Artist (P2)"
        },
        {
            "fileName": "p3",
            "displayName": "Pantheon of the Sage (P3)"
        },
        {
            "fileName": "p4",
            "displayName": "Pantheon of the Knight (P4)"
        },
        {
            "fileName": "p5",
            "displayName": "Pantheon of Hallownest (P5)"
        },
        {
            "fileName": "pop",
            "displayName": "Path of Pain"
        },
        {
            "fileName": "wp-1006",
            "displayName": "White Palace (1.0.0.6)"
        }
    ],
    "Hollow Knight: Glitched": [
        {
            "fileName": "any-ag",
            "displayName": "Any% (All Glitches)"
        },
        {
            "fileName": "any-nmms",
            "displayName": "Any% (No Main Menu Storage)"
        },
        {
            "fileName": "all-skills-ag",
            "displayName": "All Skills (All Glitches)"
        },
        {
            "fileName": "low-ag",
            "displayName": "Low% (All Glitches)"
        },
        {
            "fileName": "te-ag",
            "displayName": "True Ending (All Glitches)"
        },
        {
            "fileName": "te-nmms",
            "displayName": "True Ending (No Main Menu Storage)"
        }
    ],
    "Hollow Knight Mods": [
        {
            "fileName": "all-geo-rocks",
            "displayName": "All Geo Rocks"
        },
        {
            "fileName": "fc-as-te",
            "displayName": "Forgotten Corners AS TE"
        },
        {
            "fileName": "grass",
            "displayName": "Grass%"
        },
        {
            "fileName": "kronk",
            "displayName": "Kronk%"
        }
    ],
    "Hollow Knight Category Extensions": [
        {
            "fileName": "0geo",
            "displayName": "0 Geo"
        },
        {
            "fileName": "3vf",
            "displayName": "3 Vessel Fragments"
        },
        {
            "fileName": "worldsoul",
            "displayName": "Worldsoul (9 Vessel Fragments)"
        },
        {
            "fileName": "4ms",
            "displayName": "4 Mask Shards"
        },
        {
            "fileName": "4ms-0geo",
            "displayName": "4 Mask Shards 0 Geo"
        },
        {
            "fileName": "16ms",
            "displayName": "16 Mask Shards"
        },
        {
            "fileName": "all-breakable-charms",
            "displayName": "All Breakable Charms"
        },
        {
            "fileName": "acn",
            "displayName": "All Charm Notches"
        },
        {
            "fileName": "acn-1221",
            "displayName": "All Charm Notches (1.2.2.1)"
        },
        {
            "fileName": "all-hallownest-seals",
            "displayName": "All Hallownest Seals"
        },
        {
            "fileName": "all-stag-stations",
            "displayName": "All Stag Stations"
        },
        {
            "fileName": "all-unbreakable-charms",
            "displayName": "All Unbreakable Charms"
        },
        {
            "fileName": "all-unbreakable-charms-ss",
            "displayName": "All Unbreakable Charms (Steel Soul)"
        },
        {
            "fileName": "all-whispering-roots",
            "displayName": "All Whispering Roots"
        },
        {
            "fileName": "aluba",
            "displayName": "Aluba%"
        },
        {
            "fileName": "al2ba",
            "displayName": "Al2ba%"
        },
        {
            "fileName": "cartographer",
            "displayName": "Cartographer (a.k.a. Dapper Mapper)"
        },
        {
            "fileName": "eat-me-too",
            "displayName": "Eat Me Too"
        },
        {
            "fileName": "elderbug",
            "displayName": "Elderbug%"
        },
        {
            "fileName": "elegy",
            "displayName": "Elegy%"
        },
        {
            "fileName": "enraged-guardian",
            "displayName": "Enraged Guardian%"
        },
        {
            "fileName": "fool",
            "displayName": "Fool%"
        },
        {
            "fileName": "ggg",
            "displayName": "Gaslight, Gatekeep, Girlboss"
        },
        {
            "fileName": "gpz",
            "displayName": "GPZ%"
        },
        {
            "fileName": "great-hopper",
            "displayName": "Great Hopper%"
        },
        {
            "fileName": "happy-couple",
            "displayName": "Happy Couple"
        },
        {
            "fileName": "happy-couple-1221",
            "displayName": "Happy Couple (1.2.2.1)"
        },
        {
            "fileName": "hiveblood",
            "displayName": "Hiveblood%"
        },
        {
            "fileName": "lbc",
            "displayName": "Lifeblood Core%"
        },
        {
            "fileName": "low-ab",
            "displayName": "Low% All Bindings"
        },
        {
            "fileName": "marissa-audience",
            "displayName": "Marissa Audience"
        },
        {
            "fileName": "marmu",
            "displayName": "Marmu%"
        },
        {
            "fileName": "mr-mushroom-ending",
            "displayName": "Mr. Mushroom Ending"
        },
        {
            "fileName": "myla",
            "displayName": "Myla%"
        },
        {
            "fileName": "mylas-revenge",
            "displayName": "Myla's Revenge"
        },
        {
            "fileName": "nice",
            "displayName": "Nice% (1.2.2.1)"
        },
        {
            "fileName": "nkg",
            "displayName": "NKG%"
        },
        {
            "fileName": "nmg",
            "displayName": "NMG%"
        },
        {
            "fileName": "nosk",
            "displayName": "Nosk%"
        },
        {
            "fileName": "pop-percent",
            "displayName": "Path of Pain%"
        },
        {
            "fileName": "p5bo",
            "displayName": "Pantheon 5 Boss Order"
        },
        {
            "fileName": "p5bo-breaks",
            "displayName": "Pantheon 5 Boss Order (manual rest break splits)"
        },
        {
            "fileName": "shriek",
            "displayName": "Shriek%"
        },
        {
            "fileName": "spelless",
            "displayName": "Spelless"
        },
        {
            "fileName": "spelless-low",
            "displayName": "Low% Spelless"
        },
        {
            "fileName": "spelless-te",
            "displayName": "Spelless True Ending"
        },
        {
            "fileName": "zote",
            "displayName": "Zote%"
        }
    ]
}
